build/lib/ka_uts_com/__init__.py
build/lib/ka_uts_com/__version__.py
build/lib/ka_uts_com/com.py
build/lib/ka_uts_com/ioc.py
build/lib/ka_uts_com/log.py
build/lib/ka_uts_com/pacmod.py
build/lib/ka_uts_com/py.typed
build/lib/ka_uts_com/timer.py
build/lib/ka_uts_com/data/__init__.py
build/lib/ka_uts_com/data/log.main.tenant.yml
build/lib/ka_uts_com/data/log.person.yml
build/lib/ka_uts_com/data/log.yml
ka_uts_com/__init__.py
ka_uts_com/__version__.py
ka_uts_com/com.py
ka_uts_com/ioc.py
ka_uts_com/log.py
ka_uts_com/pacmod.py
ka_uts_com/py.typed
ka_uts_com/timer.py
ka_uts_com/data/__init__.py
ka_uts_com/data/log.main.tenant.yml
ka_uts_com/data/log.person.yml
ka_uts_com/data/log.yml
ka_uts_com-2023.6.0.dist-info/LICENSE.txt
ka_uts_com-2023.6.0.dist-info/METADATA
ka_uts_com-2023.6.0.dist-info/WHEEL
ka_uts_com-2023.6.0.dist-info/top_level.txt
ka_uts_com-2023.6.0.dist-info/RECORD
