Metadata-Version: 2.1
Name: ka_uts_com
Version: 2023.6.0
Summary: Communication Class Utilities
Author-email: Bernd Stroehle <bernd.stroehle@bs29.com>
Maintainer-email: Bernd Stroehle <bernd.stroehle@bs29.com>
Project-URL: Source Code, https://github.com/bs29/ka_uts_com/tree/master
Project-URL: Homepage, https://kosakya.de/
Project-URL: Documentation, https://ka-com.readthedocs.io/en/latest
Project-URL: Apache-2.0 License, https://apache.org/licenses/LICENSE-2.0
Classifier: Development Status :: 5 - Production/Stable
Classifier: Intended Audience :: Developers
Classifier: License :: OSI Approved :: Apache Software License
Classifier: Operating System :: OS Independent
Classifier: Programming Language :: Python :: 3.10
Classifier: Natural Language :: English
Classifier: Topic :: Software Development :: Libraries :: Python Modules
Requires-Python: >=3.10
License-File: LICENSE.txt
Requires-Dist: Jinja2>=3.1.4
Requires-Dist: PyYAML>=6.0.2
Requires-Dist: setuptools>=70.1.1
